cuneiform_sdk/__init__.py
cuneiform_sdk/cli.py
cuneiform_sdk/exceptions.py
cuneiform_sdk/scanner.py
cuneiform_sdk/core/__init__.py
cuneiform_sdk/core/context.py
cuneiform_sdk/core/decorators.py
cuneiform_sdk/core/metadata.py
cuneiform_sdk/core/schema.py
cuneiform_sdk/impl/__init__.py
cuneiform_sdk/impl/duckdb_context.py
cuneiform_sdk-0.1.3.dist-info/METADATA
cuneiform_sdk-0.1.3.dist-info/WHEEL
cuneiform_sdk-0.1.3.dist-info/entry_points.txt
cuneiform_sdk-0.1.3.dist-info/top_level.txt
cuneiform_sdk-0.1.3.dist-info/RECORD
