Metadata-Version: 2.4
Name: cuneiform-sdk
Version: 0.1.3
Summary: Enterprise-grade Python SDK for data processing workflows with AWS Lambda-style interfaces.
Author: Peernova inc.
License: MIT
Project-URL: Homepage, https://peernova.com
Project-URL: Repository, https://peernova.com
Keywords: sdk,workflow,duckdb,sql
Classifier: Programming Language :: Python :: 3
Classifier: License :: OSI Approved :: MIT License
Classifier: Operating System :: OS Independent
Requires-Python: >=3.10
Requires-Dist: duckdb
Requires-Dist: pandas
Requires-Dist: click
Requires-Dist: requests
Requires-Dist: PyYAML
Requires-Dist: sqlglot
Requires-Dist: kestra
